mediasorter/__init__.py
mediasorter/console.py
mediasorter/sorter.py
mediasorter-0.1.3.dist-info/LICENSE
mediasorter-0.1.3.dist-info/METADATA
mediasorter-0.1.3.dist-info/WHEEL
mediasorter-0.1.3.dist-info/entry_points.txt
mediasorter-0.1.3.dist-info/top_level.txt
mediasorter-0.1.3.dist-info/RECORD
